pybm3d/__init__.py
pybm3d/bm3d.cpython-36m-darwin.so
pybm3d-0.2.1.dist-info/DESCRIPTION.rst
pybm3d-0.2.1.dist-info/METADATA
pybm3d-0.2.1.dist-info/RECORD
pybm3d-0.2.1.dist-info/WHEEL
pybm3d-0.2.1.dist-info/metadata.json
pybm3d-0.2.1.dist-info/top_level.txt
