Metadata-Version: 2.0
Name: pybm3d
Version: 0.2.1
Summary: Python wrapper around BM3D
Home-page: https://github.com/ericmjonas/pybm3d
Author: Tim Meinhardt
Author-email: meinhardt.tim@gmail.com
License: UNKNOWN
Download-URL: https://github.com/ericmjonas/pybm3d/releases/download/v0.2.1/pybm3d-0.2.1.tar.gz
Platform: UNKNOWN
Requires-Dist: setuptools (>=18.0)
Requires-Dist: cython (>=0.27)
Requires-Dist: numpy (>=1.13)
